README.rst
setup.py
ptime/__init__.py
ptime.egg-info/PKG-INFO
ptime.egg-info/SOURCES.txt
ptime.egg-info/dependency_links.txt
ptime.egg-info/not-zip-safe
ptime.egg-info/top_level.txt