Metadata-Version: 1.0
Name: ptime
Version: 0.0.1
Summary: IPython magic for parallel profiling
Home-page: http://github.com/jcrist/ptime/
Author: Jim Crist
Author-email: jiminy.crist@gmail.com
License: BSD
Platform: UNKNOWN
